motivate1234/__init__.py
motivate1234/me.py
motivate1234-0.0.4.dist-info/METADATA
motivate1234-0.0.4.dist-info/WHEEL
motivate1234-0.0.4.dist-info/top_level.txt
motivate1234-0.0.4.dist-info/RECORD
