Metadata-Version: 2.1
Name: motivate1234
Version: 0.0.4
Summary: this is a new version
Home-page: UNKNOWN
Author: UNKNOWN
Author-email: UNKNOWN
License: UNKNOWN
Platform: UNKNOWN
